ysaqml/__init__.py
ysaqml/dialect.py
ysaqml/engine.py
ysaqml/py.typed
ysaqml/sync.py
ysaqml-2025.12.6.post4.dist-info/METADATA
ysaqml-2025.12.6.post4.dist-info/WHEEL
ysaqml-2025.12.6.post4.dist-info/entry_points.txt
ysaqml-2025.12.6.post4.dist-info/licenses/LICENSE
ysaqml-2025.12.6.post4.dist-info/RECORD
