Metadata-Version: 2.4
Name: ysaqml
Version: 2025.12.6.post4
Summary: ysaqml provides a YAML-backed persistence layer for SQLAlchemy.
Author-email: rbroderi <richard.broderick@gmail.com>
License: LGPL-3.0-or-later
License-File: LICENSE
Classifier: Operating System :: MacOS :: MacOS X
Classifier: Operating System :: Microsoft :: Windows
Classifier: Operating System :: POSIX :: Linux
Classifier: Programming Language :: Python :: 3
Classifier: Programming Language :: Python :: 3 :: Only
Classifier: Programming Language :: Python :: 3.13
Classifier: Programming Language :: Python :: Implementation :: CPython
Classifier: Programming Language :: Python :: Implementation :: PyPy
Requires-Python: >=3.13
Requires-Dist: naay>=2025.12.6.post0
Requires-Dist: sqlalchemy>=2.0
Provides-Extra: beartype
Requires-Dist: beartype>=0.22.8; extra == 'beartype'
Provides-Extra: dev
Requires-Dist: mypy>=1.19.0; extra == 'dev'
Requires-Dist: pytest>=9.0.1; extra == 'dev'
Requires-Dist: ruff>=0.14.7; extra == 'dev'
